setup.cfg
setup.py
gems/__init__.py
gems_mdo.egg-info/PKG-INFO
gems_mdo.egg-info/SOURCES.txt
gems_mdo.egg-info/dependency_links.txt
gems_mdo.egg-info/top_level.txt