Metadata-Version: 1.1
Name: gems-mdo
Version: 0.0.0
Summary: GEMS-MDO
Home-page: UNKNOWN
Author: IRT Saint-Exupéry
Author-email: UNKNOWN
License: UNKNOWN
Platform: UNKNOWN
Classifier: Development Status :: 1 - Planning
Classifier: Intended Audience :: Science/Research
Classifier: Programming Language :: Python
Classifier: Topic :: Scientific/Engineering
